{"format":"visual-proof-theory","version":1,"relations":{},"theorems":[{"name":"onePlusOne","lhs":{"diagram":{"root":"r0","regions":{"r0":{"kind":"sheet"}},"nodes":{},"wires":{}},"boundary":[]},"rhs":{"diagram":{"root":"r0","regions":{"r0":{"kind":"sheet"}},"nodes":{"r0_intro":{"kind":"term","region":"r0","term":"A(A(L(L(L(L(A(A(#3,#1),A(A(#2,#1),#0)))))),L(L(A(#1,#0)))),L(L(A(#1,#0))))"},"r0_intro_0":{"kind":"term","region":"r0","term":"L(L(A(#1,A(#1,#0))))"}},"wires":{"r0_intro":{"scope":"r0","endpoints":[{"node":"r0_intro","port":"out"},{"node":"r0_intro_0","port":"out"}]}}},"boundary":[]},"actions":[{"label":"one plus one 1","steps":[{"rule":"closedTermIntro","region":"r0","term":"A(A(L(L(L(L(A(A(#3,#1),A(A(#2,#1),#0)))))),L(L(A(#1,#0)))),L(L(A(#1,#0))))"}],"placements":[]},{"label":"one plus one 2","steps":[{"rule":"closedTermIntro","region":"r0","term":"L(L(A(#1,A(#1,#0))))"}],"placements":[]},{"label":"join equal terms","steps":[{"rule":"congruenceJoin","a":"r0_intro","b":"r0_intro_0","certificate":{"leftSteps":[{"kind":"beta","path":["fn"]},{"kind":"beta","path":[]},{"kind":"beta","path":["body","body","fn"]},{"kind":"beta","path":["body","body"]},{"kind":"beta","path":["body","body","arg","fn"]},{"kind":"beta","path":["body","body","arg"]}],"rightSteps":[]}}],"placements":[]}]},{"name":"fixedPoint","lhs":{"diagram":{"root":"r0","regions":{"r0":{"kind":"sheet"}},"nodes":{"n0":{"kind":"term","region":"r0","term":"A(L(A(L(A(#1,A(#0,#0))),L(A(#1,A(#0,#0))))),P(\"s0\"))"}},"wires":{"w0":{"scope":"r0","endpoints":[{"node":"n0","port":"out"}]},"w1":{"scope":"r0","endpoints":[{"node":"n0","port":"v:s0"}]}}},"boundary":["w0","w1"]},"rhs":{"diagram":{"root":"r0","regions":{"r0":{"kind":"sheet"}},"nodes":{"n0":{"kind":"term","region":"r0","term":"A(P(\"s0\"),A(L(A(L(A(#1,A(#0,#0))),L(A(#1,A(#0,#0))))),P(\"s0\")))"}},"wires":{"w0":{"scope":"r0","endpoints":[{"node":"n0","port":"out"}]},"w1":{"scope":"r0","endpoints":[{"node":"n0","port":"v:s0"}]}}},"boundary":["w0","w1"]},"actions":[{"label":"unfold fixed point","steps":[{"rule":"conversion","node":"n0","term":"A(P(\"s0\"),A(L(A(L(A(#1,A(#0,#0))),L(A(#1,A(#0,#0))))),P(\"s0\")))","certificate":{"leftSteps":[{"kind":"beta","path":[]},{"kind":"beta","path":[]}],"rightSteps":[{"kind":"beta","path":["arg"]}]},"attachments":{}}],"placements":[]}]}]}
